{
  "parameters": {
    "callback": {
      "type": "string",
      "location": "query",
      "description": "JSONP"
    },
    "prettyPrint": {
      "default": "true",
      "description": "Returns response with indentations and line breaks.",
      "location": "query",
      "type": "boolean"
    },
    "pp": {
      "location": "query",
      "description": "Pretty-print response.",
      "default": "true",
      "type": "boolean"
    },
    "$.xgafv": {
      "location": "query",
      "enum": [
        "1",
        "2"
      ],
      "description": "V1 error format.",
      "enumDescriptions": [
        "v1 error format",
        "v2 error format"
      ],
      "type": "string"
    },
    "bearer_token": {
      "location": "query",
      "description": "OAuth bearer token.",
      "type": "string"
    },
    "fields": {
      "description": "Selector specifying which fields to include in a partial response.",
      "location": "query",
      "type": "string"
    },
    "quotaUser": {
      "description": "Available to use for quota purposes for server-side applications. Can be any arbitrary string assigned to a user, but should not exceed 40 characters. Overrides userIp if both are provided.",
      "location": "query",
      "type": "string"
    },
    "alt": {
      "location": "query",
      "enum": [
        "json",
        "media",
        "proto"
      ],
      "description": "Data format for response.",
      "default": "json",
      "enumDescriptions": [
        "Responses with Content-Type of application/json",
        "Media download with context-dependent Content-Type",
        "Responses with Content-Type of application/x-protobuf"
      ],
      "type": "string"
    },
    "key": {
      "type": "string",
      "location": "query",
      "description": "API key. Your API key identifies your project and provides you with API access, quota, and reports. Required unless you provide an OAuth 2.0 token."
    },
    "access_token": {
      "location": "query",
      "type": "string",
      "description": "OAuth access token."
    },
    "uploadType": {
      "type": "string",
      "location": "query",
      "description": "Legacy upload protocol for media (e.g. \"media\", \"multipart\")."
    },
    "upload_protocol": {
      "type": "string",
      "description": "Upload protocol for media (e.g. \"raw\", \"multipart\").",
      "location": "query"
    },
    "oauth_token": {
      "location": "query",
      "type": "string",
      "description": "OAuth 2.0 token for the current user."
    }
  },
  "protocol": "rest",
  "servicePath": "language/translate/",
  "resources": {
    "languages": {
      "methods": {
        "list": {
          "response": {
            "$ref": "LanguagesListResponse"
          },
          "parameters": {
            "target": {
              "type": "string",
              "description": "The language to use to return localized, human readable names of supported\nlanguages.",
              "location": "query"
            },
            "model": {
              "location": "query",
              "description": "The model type for which supported languages should be returned.",
              "type": "string"
            }
          },
          "id": "language.languages.list",
          "scopes": [
            "https://www.googleapis.com/auth/cloud-translation",
            "https://www.googleapis.com/auth/cloud-platform"
          ],
          "path": "v2/languages",
          "description": "Returns a list of supported languages for translation.",
          "httpMethod": "GET"
        }
      }
    },
    "translations": {
      "methods": {
        "translate": {
          "parameters": {},
          "parameterOrder": [],
          "request": {
            "$ref": "TranslateTextRequest"
          },
          "path": "v2",
          "scopes": [
            "https://www.googleapis.com/auth/cloud-translation",
            "https://www.googleapis.com/auth/cloud-platform"
          ],
          "response": {
            "$ref": "TranslationsListResponse"
          },
          "id": "language.translations.translate",
          "httpMethod": "POST",
          "description": "Translates input text, returning translated text."
        },
        "list": {
          "description": "Translates input text, returning translated text.",
          "path": "v2",
          "scopes": [
            "https://www.googleapis.com/auth/cloud-translation",
            "https://www.googleapis.com/auth/cloud-platform"
          ],
          "parameterOrder": [
            "q",
            "target"
          ],
          "response": {
            "$ref": "TranslationsListResponse"
          },
          "parameters": {
            "format": {
              "enumDescriptions": [
                "Specifies the input is in HTML",
                "Specifies the input is in plain textual format"
              ],
              "description": "The format of the source text, in either HTML (default) or plain-text. A\nvalue of \"html\" indicates HTML and a value of \"text\" indicates plain-text.",
              "location": "query",
              "type": "string",
              "enum": [
                "html",
                "text"
              ]
            },
            "target": {
              "description": "The language to use for translation of the input text, set to one of the\nlanguage codes listed in Language Support.",
              "location": "query",
              "type": "string",
              "required": true
            },
            "q": {
              "type": "string",
              "required": true,
              "description": "The input text to translate. Repeat this parameter to perform translation\noperations on multiple text inputs.",
              "location": "query",
              "repeated": true
            },
            "source": {
              "description": "The language of the source text, set to one of the language codes listed in\nLanguage Support. If the source language is not specified, the API will\nattempt to identify the source language automatically and return it within\nthe response.",
              "type": "string",
              "location": "query"
            },
            "model": {
              "location": "query",
              "description": "The `model` type requested for this translation. Valid values are\nlisted in public documentation.",
              "type": "string"
            },
            "cid": {
              "location": "query",
              "description": "The customization id for translate",
              "type": "string",
              "repeated": true
            }
          },
          "id": "language.translations.list",
          "httpMethod": "GET"
        }
      }
    },
    "detections": {
      "methods": {
        "list": {
          "path": "v2/detect",
          "id": "language.detections.list",
          "response": {
            "$ref": "DetectionsListResponse"
          },
          "scopes": [
            "https://www.googleapis.com/auth/cloud-translation",
            "https://www.googleapis.com/auth/cloud-platform"
          ],
          "parameters": {
            "q": {
              "type": "string",
              "description": "The input text upon which to perform language detection. Repeat this\nparameter to perform language detection on multiple text inputs.",
              "location": "query",
              "required": true,
              "repeated": true
            }
          },
          "parameterOrder": [
            "q"
          ],
          "httpMethod": "GET",
          "description": "Detects the language of text within a request."
        },
        "detect": {
          "response": {
            "$ref": "DetectionsListResponse"
          },
          "description": "Detects the language of text within a request.",
          "request": {
            "$ref": "DetectLanguageRequest"
          },
          "httpMethod": "POST",
          "scopes": [
            "https://www.googleapis.com/auth/cloud-translation",
            "https://www.googleapis.com/auth/cloud-platform"
          ],
          "parameters": {},
          "path": "v2/detect",
          "parameterOrder": [],
          "id": "language.detections.detect"
        }
      }
    }
  },
  "documentationLink": "https://code.google.com/apis/language/translate/v2/getting_started.html",
  "rootUrl": "https://translation.googleapis.com/",
  "description": "The Google Cloud Translation API lets websites and programs integrate with\n    Google Translate programmatically.",
  "schemas": {
    "DetectionsResource": {
      "type": "array",
      "description": "An array of languages which we detect for the given text The most likely language list first.",
      "id": "DetectionsResource",
      "items": {
        "type": "object",
        "properties": {
          "isReliable": {
            "description": "A boolean to indicate is the language detection result reliable.",
            "type": "boolean"
          },
          "confidence": {
            "description": "The confidence of the detection result of this language.",
            "type": "number",
            "format": "float"
          },
          "language": {
            "type": "string",
            "description": "The language we detected."
          }
        }
      }
    },
    "LanguagesResource": {
      "type": "object",
      "id": "LanguagesResource",
      "properties": {
        "name": {
          "description": "Human readable name of the language localized to the target language.",
          "type": "string"
        },
        "language": {
          "description": "Supported language code, generally consisting of its ISO 639-1\nidentifier. (E.g. 'en', 'ja'). In certain cases, BCP-47 codes including\nlanguage + region identifiers are returned (e.g. 'zh-TW' and 'zh-CH')",
          "type": "string"
        }
      }
    },
    "LanguagesListResponse": {
      "type": "object",
      "properties": {
        "languages": {
          "items": {
            "$ref": "LanguagesResource"
          },
          "type": "array",
          "description": "List of source/target languages supported by the translation API. If target parameter is unspecified, the list is sorted by the ASCII code point order of the language code. If target parameter is specified, the list is sorted by the collation order of the language name in the target language."
        }
      },
      "id": "LanguagesListResponse"
    },
    "GetSupportedLanguagesRequest": {
      "type": "object",
      "description": "The request message for discovering supported languages.",
      "properties": {
        "target": {
          "description": "The language to use to return localized, human readable names of supported\nlanguages.",
          "type": "string"
        }
      },
      "id": "GetSupportedLanguagesRequest"
    },
    "DetectLanguageRequest": {
      "properties": {
        "q": {
          "items": {
            "type": "string"
          },
          "description": "The input text upon which to perform language detection. Repeat this\nparameter to perform language detection on multiple text inputs.",
          "type": "array"
        }
      },
      "type": "object",
      "id": "DetectLanguageRequest",
      "description": "The request message for language detection."
    },
    "TranslationsResource": {
      "properties": {
        "detectedSourceLanguage": {
          "description": "The source language of the initial request, detected automatically, if\nno source language was passed within the initial request. If the\nsource language was passed, auto-detection of the language will not\noccur and this field will be empty.",
          "type": "string"
        },
        "model": {
          "description": "The `model` type used for this translation. Valid values are\nlisted in public documentation. Can be different from requested `model`.\nPresent only if specific model type was explicitly requested.",
          "type": "string"
        },
        "translatedText": {
          "description": "Text translated into the target language.",
          "type": "string"
        }
      },
      "id": "TranslationsResource",
      "type": "object"
    },
    "TranslateTextRequest": {
      "properties": {
        "model": {
          "description": "The `model` type requested for this translation. Valid values are\nlisted in public documentation.",
          "type": "string"
        },
        "target": {
          "type": "string",
          "description": "The language to use for translation of the input text, set to one of the\nlanguage codes listed in Language Support."
        },
        "source": {
          "type": "string",
          "description": "The language of the source text, set to one of the language codes listed in\nLanguage Support. If the source language is not specified, the API will\nattempt to identify the source language automatically and return it within\nthe response."
        },
        "q": {
          "type": "array",
          "items": {
            "type": "string"
          },
          "description": "The input text to translate. Repeat this parameter to perform translation\noperations on multiple text inputs."
        },
        "format": {
          "type": "string",
          "description": "The format of the source text, in either HTML (default) or plain-text. A\nvalue of \"html\" indicates HTML and a value of \"text\" indicates plain-text."
        }
      },
      "type": "object",
      "description": "The main translation request message for the Cloud Translation API.",
      "id": "TranslateTextRequest"
    },
    "DetectionsListResponse": {
      "properties": {
        "detections": {
          "items": {
            "$ref": "DetectionsResource"
          },
          "type": "array",
          "description": "A detections contains detection results of several text"
        }
      },
      "type": "object",
      "id": "DetectionsListResponse"
    },
    "TranslationsListResponse": {
      "id": "TranslationsListResponse",
      "type": "object",
      "description": "The main language translation response message.",
      "properties": {
        "translations": {
          "type": "array",
          "description": "Translations contains list of translation results of given text",
          "items": {
            "$ref": "TranslationsResource"
          }
        }
      }
    }
  },
  "canonicalName": "Translate",
  "name": "translate",
  "icons": {
    "x32": "https://www.google.com/images/icons/product/translate-32.png",
    "x16": "https://www.google.com/images/icons/product/translate-16.png"
  },
  "title": "Google Cloud Translation API",
  "batchPath": "batch/translate",
  "revision": "20170525",
  "features": [
    "dataWrapper"
  ],
  "kind": "discovery#restDescription",
  "ownerDomain": "google.com",
  "auth": {
    "oauth2": {
      "scopes": {
        "https://www.googleapis.com/auth/cloud-platform": {
          "description": "View and manage your data across Google Cloud Platform services"
        },
        "https://www.googleapis.com/auth/cloud-translation": {
          "description": "Translate text from one language to another using Google Translate"
        }
      }
    }
  },
  "id": "translate:v2",
  "basePath": "/language/translate/",
  "ownerName": "Google",
  "version": "v2",
  "discoveryVersion": "v1",
  "baseUrl": "https://translation.googleapis.com/language/translate/"
}
